[
  {
    "img": "/assets/img/icons/Door01.svg",   
    "title": "Local Expertise",
    "desc": "As Ethiopia’s leading eco-door manufacturer, we provide tailored solutions designed for the local market."
  },
  {
    "img": "/assets/img/icons/Cer.png",   
    "title": "Uncompromising Quality",
    "desc": "Our doors are crafted from premium, sustainable materials, ensuring durability, elegance, and long-term value."
  },
  {
    "img": "/assets/img/icons/craft.png",   
    "title": "Bespoke Customization",
    "desc": "We offer fully customizable designs, allowing you to create doors that perfectly match your style and functional needs."
  }   
]
